skymap_job_processing/__init__.py
skymap_job_processing/processing.py
skymap_job_processing-0.4.0.dist-info/METADATA
skymap_job_processing-0.4.0.dist-info/WHEEL
skymap_job_processing-0.4.0.dist-info/top_level.txt
skymap_job_processing-0.4.0.dist-info/RECORD
