Metadata-Version: 2.1
Name: skymap-job-processing
Version: 0.4.0
Requires-Dist: requests
Requires-Dist: websockets
